[
  {
    "major": [
      {
        "title":"영업",
        "link":"#"
      }
    ],
    "sub":[
      {
        "title":"기업영업", 
        "link":"#"
      },
      {
        "title":"외부영업",
        "link":"#"
      },
      {
        "title":"영업관리자",
        "link":"#"
      },
      {
        "title":"기술영업",
        "link":"#"
      },
      {
        "title":"기술영업",
        "link":"#"
      },
      {
        "title":"주요고객사 담당자",
        "link":"#"
      },
      {
        "title":"솔루션 컨설턴트",
        "link":"#"
      },
      {
        "title":"해외영업",
        "link":"#"
      }
    ],
    "more":"#"
  },
  {
    "major": [
      {
        "title":"미디어",
        "link":"#"
      }
    ],
    "sub":[
      {
        "title":"콘텐츠 크리에이터", 
        "link":"#"
      },
      {
        "title":"피디",
        "link":"#"
      },
      {
        "title":"영상편집가",
        "link":"#"
      },
      {
        "title":"에디터",
        "link":"#"
      },
      {
        "title":"비디오제작",
        "link":"#"
      },
      {
        "title":"작가",
        "link":"#"
      },
      {
        "title":"출판 기획사",
        "link":"#"
      }
    ],
    "more":"#"
  },
  {
    "major": [
      {
        "title":"인사",
        "link":"#"
      }
    ],
    "sub":[
      {
        "title":"인사담당", 
        "link":"#"
      },
      {
        "title":"리쿠루터",
        "link":"#"
      },
      {
        "title":"조직문화",
        "link":"#"
      },
      {
        "title":"평가보상",
        "link":"#"
      },
      {
        "title":"헤드헌터",
        "link":"#"
      },
      {
        "title":"HRD",
        "link":"#"
      },
      {
        "title":"HRBP",
        "link":"#"
      }
    ],
    "more":"#"
  },
  {
    "major": [
      {
        "title":"게임제작",
        "link":"#"
      }
    ],
    "sub":[
      {
        "title":"게임 기획자", 
        "link":"#"
      },
      {
        "title":"게임 그래픽 디자이너",
        "link":"#"
      },
      {
        "title":"모바일 게임 개발자",
        "link":"#"
      },
      {
        "title":"게임 클라이언트 개발자",
        "link":"#"
      },
      {
        "title":"게임 아티스트",
        "link":"#"
      },
      {
        "title":"유니티 개발자",
        "link":"#"
      },
      {
        "title":"게임 서버 개발자",
        "link":"#"
      }
    ],
    "more":"#"
  },
  {
    "major": [
      {
        "title":"금융",
        "link":"#"
      }
    ],
    "sub":[
      {
        "title":"회계 담당", 
        "link":"#"
      },
      {
        "title":"재무 담당자",
        "link":"#"
      },
      {
        "title":"IR",
        "link":"#"
      },
      {
        "title":"투자증권",
        "link":"#"
      },
      {
        "title":"재무분석가",
        "link":"#"
      },
      {
        "title":"애널리스트",
        "link":"#"
      },
      {
        "title":"내부통제 담당자",
        "link":"#"
      }
    ],
    "more":"#"
  },
  {
    "major": [
      {
        "title":"엔지니리어링 설계",
        "link":"#"
      },
      {
        "title":"물류 무역",
        "link":"#"
      },
      {
        "title":"제조 생상",
        "link":"#"
      },
      {
        "title":"의료 바이오",
        "link":"#"
      },
      {
        "title":"교육",
        "link":"#"
      },
      {
        "title":"법률 법집행기관",
        "link":"#"
      },
      {
        "title":"식 음료",
        "link":"#"
      },
      {
        "title":"건설 시설",
        "link":"#"
      },
      {
        "title":"공공 복지",
        "link":"#"
      }
    ]
  }
]